Workbook

Sheet Features
A1: # | B1: Category | C1: Sub | D1: Feature | E1: Description | F1: Where | G1: Shipped (SaaS) | H1: Phase | I1: Apex Effort | J1: Deployed (Package) | K1: Migration Notes
A2: 1 | B2: Engine Core | C2: Schema | D2: ForensicScan custom object | E2: Per-scan record: status, started_at, completed_at, totals | F2: DB → SF custom object | G2: Yes | H2: v1.0 | I2: Easy | J2: No | K2: Becomes ForensicScan__c with picklist Status + summary fields.
A3: 2 | B3: Engine Core | C3: Schema | D3: ForensicFinding custom object | E3: Per-finding row: detector_id, gap_usd, status, hidden_at, consultant_note | F3: DB → SF custom object | G3: Yes | H3: v1.0 | I3: Easy | J3: No | K3: Becomes ForensicFinding__c. ~12 custom fields including evidence as Long Text Area.
A4: 3 | B4: Engine Core | C4: Schema | D4: AttributionTrace custom object | E4: Root-cause trace: class, config, evidence, AI explanation | F4: DB → SF custom object | G4: Yes | H4: v1.0 | I4: Medium | J4: No | K4: AttributionTrace__c with junction to ForensicFinding__c.
A5: 4 | B5: Engine Core | C5: Schema | D5: RecoveryAction custom object | E5: State machine: pending → approved → committed | F5: DB → SF custom object | G5: Yes | H5: v1.0 | I5: Medium | J5: No | K5: RecoveryAction__c + Apex trigger for state transitions.
A6: 5 | B6: Engine Core | C6: Schema | D6: CheckSuppression custom object | E6: Per-org false-positive memory: future scans skip suppressed checks | F6: DB → SF custom object | G6: Yes | H6: v1.5 | I6: Easy | J6: No | K6: CheckSuppression__c keyed (org, check_id).
A7: 6 | B7: Engine Core | C7: Scan | D7: Background scan job + chaining | E7: Long-running scan + chains forensic scan after config scan | F7: src/lib/scans/run-scan-in-background.ts | G7: Yes | H7: v1.0 | I7: Medium | J7: No | K7: Queueable + Batchable Apex chain. 5-min sync limit watch.
A8: 7 | B8: Engine Core | C8: Scan | D8: Scan dialog with forensics opt-in | E8: UI to kick off a scan with deep-scan checkbox | F8: src/components/scan/scan-dialog.tsx | G8: Yes | H8: v1.0 | I8: Easy | J8: No | K8: LWC modal + toggle.
A9: 8 | B9: Engine Core | C9: AI | D9: Plain-English finding renderer (Gemini) | E9: AI-generated explanation per finding, grounded in evidence | F9: src/lib/forensics/renderer.ts | G9: Yes | H9: v2.5 | I9: Hard | J9: No | K9: Apex Named Credential → Gemini. Governor limits cap throughput. Pre-compute via batch + cache.
A10: 9 | B10: Engine Core | C10: API | D10: Bulk API 2.0 client wrapper | E10: Stream-friendly SF Bulk API 2.0 wrapper | F10: src/lib/salesforce/bulk-client.ts | G10: Yes | H10: Skip | I10: Skip | J10: No | K10: In-package uses native SOQL — no Bulk wrapper needed.
A11: 10 | B11: Engine Core | C11: API | D11: jsforce + token refresh + retry | E11: createRefreshableConnection wrapper with revoke-detection | F11: src/lib/salesforce/client.ts | G11: Yes | H11: Skip | I11: Skip | J11: No | K11: N/A — Apex runs as the user.
A12: 11 | B12: Engine Core | C12: API | D12: Empty-error guard (revoked-token detection) | E12: jsforce empty-message Error → actionable reconnect message | F12: 4 API routes | G12: Yes | H12: Skip | I12: Skip | J12: No | K12: N/A in-package.
A13: 12 | B13: Detectors | C13: Renewals | D13: REN-001 — Renewal Uplift Suppressed | E13: Renewal Quote Lines where contractually entitled uplift not applied | F13: src/lib/forensics/detectors/ren-001-renewal-uplift.ts | G13: Yes | H13: v1.0 | I13: Easy | J13: No | K13: Highest-$ detector. Phase 1 MVP.
... A154: 153 | B154: Infra | C154: Diag | D154: Detector verification report script | E154: Audits all 20 detectors against CPQ Ks demo data | F154: scripts/verify-all-detectors.ts | G154: Yes | H154: Skip | I154: Skip | J154: No | K154: Dev tool — N/A in-package.

Sheet Summary
A1: Category | B1: Features | C1: Deployed | D1: % Deployed | E1: v1.0 | F1: v1.5 | G1: v2.0 | H1: v2.5 | I1: v3.0+ | J1: Skip
A2: Engine Core | B2: =COUNTIF(Features!B:B,"Engine Core") | C2: =COUNTIFS(Features!B:B,"Engine Core",Features!J:J,"Yes") | D2: =IFERROR(C2/B2,0) | E2: =COUNTIFS(Features!B:B,"Engine Core",Features!H:H,"v1.0") | F2: =COUNTIFS(Features!B:B,"Engine Core",Features!H:H,"v1.5") | G2: =COUNTIFS(Features!B:B,"Engine Core",Features!H:H,"v2.0") | H2: =COUNTIFS(Features!B:B,"Engine Core",Features!H:H,"v2.5") | I2: =COUNTIFS(Features!B:B,"Engine Core",Features!H:H,"v3.0+") | J2: =COUNTIFS(Features!B:B,"Engine Core",Features!H:H,"Skip")
A3: Detectors | B3: =COUNTIF(Features!B:B,"Detectors") | C3: =COUNTIFS(Features!B:B,"Detectors",Features!J:J,"Yes") | D3: =IFERROR(C3/B3,0) | E3: =COUNTIFS(Features!B:B,"Detectors",Features!H:H,"v1.0") | F3: =COUNTIFS(Features!B:B,"Detectors",Features!H:H,"v1.5") | G3: =COUNTIFS(Features!B:B,"Detectors",Features!H:H,"v2.0") | H3: =COUNTIFS(Features!B:B,"Detectors",Features!H:H,"v2.5") | I3: =COUNTIFS(Features!B:B,"Detectors",Features!H:H,"v3.0+") | J3: =COUNTIFS(Features!B:B,"Detectors",Features!H:H,"Skip")
A4: Attribution | B4: =COUNTIF(Features!B:B,"Attribution") | C4: =COUNTIFS(Features!B:B,"Attribution",Features!J:J,"Yes") | D4: =IFERROR(C4/B4,0) | E4: =COUNTIFS(Features!B:B,"Attribution",Features!H:H,"v1.0") | F4: =COUNTIFS(Features!B:B,"Attribution",Features!H:H,"v1.5") | G4: =COUNTIFS(Features!B:B,"Attribution",Features!H:H,"v2.0") | H4: =COUNTIFS(Features!B:B,"Attribution",Features!H:H,"v2.5") | I4: =COUNTIFS(Features!B:B,"Attribution",Features!H:H,"v3.0+") | J4: =COUNTIFS(Features!B:B,"Attribution",Features!H:H,"Skip")
A5: Recovery | B5: =COUNTIF(Features!B:B,"Recovery") | C5: =COUNTIFS(Features!B:B,"Recovery",Features!J:J,"Yes") | D5: =IFERROR(C5/B5,0) | E5: =COUNTIFS(Features!B:B,"Recovery",Features!H:H,"v1.0") | F5: =COUNTIFS(Features!B:B,"Recovery",Features!H:H,"v1.5") | G5: =COUNTIFS(Features!B:B,"Recovery",Features!H:H,"v2.0") | H5: =COUNTIFS(Features!B:B,"Recovery",Features!H:H,"v2.5") | I5: =COUNTIFS(Features!B:B,"Recovery",Features!H:H,"v3.0+") | J5: =COUNTIFS(Features!B:B,"Recovery",Features!H:H,"Skip")
A6: Dashboard | B6: =COUNTIF(Features!B:B,"Dashboard") | C6: =COUNTIFS(Features!B:B,"Dashboard",Features!J:J,"Yes") | D6: =IFERROR(C6/B6,0) | E6: =COUNTIFS(Features!B:B,"Dashboard",Features!H:H,"v1.0") | F6: =COUNTIFS(Features!B:B,"Dashboard",Features!H:H,"v1.5") | G6: =COUNTIFS(Features!B:B,"Dashboard",Features!H:H,"v2.0") | H6: =COUNTIFS(Features!B:B,"Dashboard",Features!H:H,"v2.5") | I6: =COUNTIFS(Features!B:B,"Dashboard",Features!H:H,"v3.0+") | J6: =COUNTIFS(Features!B:B,"Dashboard",Features!H:H,"Skip")
A7: Matrix | B7: =COUNTIF(Features!B:B,"Matrix") | C7: =COUNTIFS(Features!B:B,"Matrix",Features!J:J,"Yes") | D7: =IFERROR(C7/B7,0) | E7: =COUNTIFS(Features!B:B,"Matrix",Features!H:H,"v1.0") | F7: =COUNTIFS(Features!B:B,"Matrix",Features!H:H,"v1.5") | G7: =COUNTIFS(Features!B:B,"Matrix",Features!H:H,"v2.0") | H7: =COUNTIFS(Features!B:B,"Matrix",Features!H:H,"v2.5") | I7: =COUNTIFS(Features!B:B,"Matrix",Features!H:H,"v3.0+") | J7: =COUNTIFS(Features!B:B,"Matrix",Features!H:H,"Skip")
A8: Reports | B8: =COUNTIF(Features!B:B,"Reports") | C8: =COUNTIFS(Features!B:B,"Reports",Features!J:J,"Yes") | D8: =IFERROR(C8/B8,0) | E8: =COUNTIFS(Features!B:B,"Reports",Features!H:H,"v1.0") | F8: =COUNTIFS(Features!B:B,"Reports",Features!H:H,"v1.5") | G8: =COUNTIFS(Features!B:B,"Reports",Features!H:H,"v2.0") | H8: =COUNTIFS(Features!B:B,"Reports",Features!H:H,"v2.5") | I8: =COUNTIFS(Features!B:B,"Reports",Features!H:H,"v3.0+") | J8: =COUNTIFS(Features!B:B,"Reports",Features!H:H,"Skip")
A9: Filter | B9: =COUNTIF(Features!B:B,"Filter") | C9: =COUNTIFS(Features!B:B,"Filter",Features!J:J,"Yes") | D9: =IFERROR(C9/B9,0) | E9: =COUNTIFS(Features!B:B,"Filter",Features!H:H,"v1.0") | F9: =COUNTIFS(Features!B:B,"Filter",Features!H:H,"v1.5") | G9: =COUNTIFS(Features!B:B,"Filter",Features!H:H,"v2.0") | H9: =COUNTIFS(Features!B:B,"Filter",Features!H:H,"v2.5") | I9: =COUNTIFS(Features!B:B,"Filter",Features!H:H,"v3.0+") | J9: =COUNTIFS(Features!B:B,"Filter",Features!H:H,"Skip")
A10: Bulk | B10: =COUNTIF(Features!B:B,"Bulk") | C10: =COUNTIFS(Features!B:B,"Bulk",Features!J:J,"Yes") | D10: =IFERROR(C10/B10,0) | E10: =COUNTIFS(Features!B:B,"Bulk",Features!H:H,"v1.0") | F10: =COUNTIFS(Features!B:B,"Bulk",Features!H:H,"v1.5") | G10: =COUNTIFS(Features!B:B,"Bulk",Features!H:H,"v2.0") | H10: =COUNTIFS(Features!B:B,"Bulk",Features!H:H,"v2.5") | I10: =COUNTIFS(Features!B:B,"Bulk",Features!H:H,"v3.0+") | J10: =COUNTIFS(Features!B:B,"Bulk",Features!H:H,"Skip")
A11: Hide | B11: =COUNTIF(Features!B:B,"Hide") | C11: =COUNTIFS(Features!B:B,"Hide",Features!J:J,"Yes") | D11: =IFERROR(C11/B11,0) | E11: =COUNTIFS(Features!B:B,"Hide",Features!H:H,"v1.0") | F11: =COUNTIFS(Features!B:B,"Hide",Features!H:H,"v1.5") | G11: =COUNTIFS(Features!B:B,"Hide",Features!H:H,"v2.0") | H11: =COUNTIFS(Features!B:B,"Hide",Features!H:H,"v2.5") | I11: =COUNTIFS(Features!B:B,"Hide",Features!H:H,"v3.0+") | J11: =COUNTIFS(Features!B:B,"Hide",Features!H:H,"Skip")
A12: Notes | B12: =COUNTIF(Features!B:B,"Notes") | C12: =COUNTIFS(Features!B:B,"Notes",Features!J:J,"Yes") | D12: =IFERROR(C12/B12,0) | E12: =COUNTIFS(Features!B:B,"Notes",Features!H:H,"v1.0") | F12: =COUNTIFS(Features!B:B,"Notes",Features!H:H,"v1.5") | G12: =COUNTIFS(Features!B:B,"Notes",Features!H:H,"v2.0") | H12: =COUNTIFS(Features!B:B,"Notes",Features!H:H,"v2.5") | I12: =COUNTIFS(Features!B:B,"Notes",Features!H:H,"v3.0+") | J12: =COUNTIFS(Features!B:B,"Notes",Features!H:H,"Skip")
A13: Attribution Map | B13: =COUNTIF(Features!B:B,"Attribution Map") | C13: =COUNTIFS(Features!B:B,"Attribution Map",Features!J:J,"Yes") | D13: =IFERROR(C13/B13,0) | E13: =COUNTIFS(Features!B:B,"Attribution Map",Features!H:H,"v1.0") | F13: =COUNTIFS(Features!B:B,"Attribution Map",Features!H:H,"v1.5") | G13: =COUNTIFS(Features!B:B,"Attribution Map",Features!H:H,"v2.0") | H13: =COUNTIFS(Features!B:B,"Attribution Map",Features!H:H,"v2.5") | I13: =COUNTIFS(Features!B:B,"Attribution Map",Features!H:H,"v3.0+") | J13: =COUNTIFS(Features!B:B,"Attribution Map",Features!H:H,"Skip")
A14: Tabs | B14: =COUNTIF(Features!B:B,"Tabs") | C14: =COUNTIFS(Features!B:B,"Tabs",Features!J:J,"Yes") | D14: =IFERROR(C14/B14,0) | E14: =COUNTIFS(Features!B:B,"Tabs",Features!H:H,"v1.0") | F14: =COUNTIFS(Features!B:B,"Tabs",Features!H:H,"v1.5") | G14: =COUNTIFS(Features!B:B,"Tabs",Features!H:H,"v2.0") | H14: =COUNTIFS(Features!B:B,"Tabs",Features!H:H,"v2.5") | I14: =COUNTIFS(Features!B:B,"Tabs",Features!H:H,"v3.0+") | J14: =COUNTIFS(Features!B:B,"Tabs",Features!H:H,"Skip")
A15: Issues | B15: =COUNTIF(Features!B:B,"Issues") | C15: =COUNTIFS(Features!B:B,"Issues",Features!J:J,"Yes") | D15: =IFERROR(C15/B15,0) | E15: =COUNTIFS(Features!B:B,"Issues",Features!H:H,"v1.0") | F15: =COUNTIFS(Features!B:B,"Issues",Features!H:H,"v1.5") | G15: =COUNTIFS(Features!B:B,"Issues",Features!H:H,"v2.0") | H15: =COUNTIFS(Features!B:B,"Issues",Features!H:H,"v2.5") | I15: =COUNTIFS(Features!B:B,"Issues",Features!H:H,"v3.0+") | J15: =COUNTIFS(Features!B:B,"Issues",Features!H:H,"Skip")
A16: Finding Detail | B16: =COUNTIF(Features!B:B,"Finding Detail") | C16: =COUNTIFS(Features!B:B,"Finding Detail",Features!J:J,"Yes") | D16: =IFERROR(C16/B16,0) | E16: =COUNTIFS(Features!B:B,"Finding Detail",Features!H:H,"v1.0") | F16: =COUNTIFS(Features!B:B,"Finding Detail",Features!H:H,"v1.5") | G16: =COUNTIFS(Features!B:B,"Finding Detail",Features!H:H,"v2.0") | H16: =COUNTIFS(Features!B:B,"Finding Detail",Features!H:H,"v2.5") | I16: =COUNTIFS(Features!B:B,"Finding Detail",Features!H:H,"v3.0+") | J16: =COUNTIFS(Features!B:B,"Finding Detail",Features!H:H,"Skip")
A17: UX | B17: =COUNTIF(Features!B:B,"UX") | C17: =COUNTIFS(Features!B:B,"UX",Features!J:J,"Yes") | D17: =IFERROR(C17/B17,0) | E17: =COUNTIFS(Features!B:B,"UX",Features!H:H,"v1.0") | F17: =COUNTIFS(Features!B:B,"UX",Features!H:H,"v1.5") | G17: =COUNTIFS(Features!B:B,"UX",Features!H:H,"v2.0") | H17: =COUNTIFS(Features!B:B,"UX",Features!H:H,"v2.5") | I17: =COUNTIFS(Features!B:B,"UX",Features!H:H,"v3.0+") | J17: =COUNTIFS(Features!B:B,"UX",Features!H:H,"Skip")
A18: Forensic Diff | B18: =COUNTIF(Features!B:B,"Forensic Diff") | C18: =COUNTIFS(Features!B:B,"Forensic Diff",Features!J:J,"Yes") | D18: =IFERROR(C18/B18,0) | E18: =COUNTIFS(Features!B:B,"Forensic Diff",Features!H:H,"v1.0") | F18: =COUNTIFS(Features!B:B,"Forensic Diff",Features!H:H,"v1.5") | G18: =COUNTIFS(Features!B:B,"Forensic Diff",Features!H:H,"v2.0") | H18: =COUNTIFS(Features!B:B,"Forensic Diff",Features!H:H,"v2.5") | I18: =COUNTIFS(Features!B:B,"Forensic Diff",Features!H:H,"v3.0+") | J18: =COUNTIFS(Features!B:B,"Forensic Diff",Features!H:H,"Skip")
A19: Auth / Onboarding | B19: =COUNTIF(Features!B:B,"Auth / Onboarding") | C19: =COUNTIFS(Features!B:B,"Auth / Onboarding",Features!J:J,"Yes") | D19: =IFERROR(C19/B19,0) | E19: =COUNTIFS(Features!B:B,"Auth / Onboarding",Features!H:H,"v1.0") | F19: =COUNTIFS(Features!B:B,"Auth / Onboarding",Features!H:H,"v1.5") | G19: =COUNTIFS(Features!B:B,"Auth / Onboarding",Features!H:H,"v2.0") | H19: =COUNTIFS(Features!B:B,"Auth / Onboarding",Features!H:H,"v2.5") | I19: =COUNTIFS(Features!B:B,"Auth / Onboarding",Features!H:H,"v3.0+") | J19: =COUNTIFS(Features!B:B,"Auth / Onboarding",Features!H:H,"Skip")
A20: Team & Portfolio | B20: =COUNTIF(Features!B:B,"Team & Portfolio") | C20: =COUNTIFS(Features!B:B,"Team & Portfolio",Features!J:J,"Yes") | D20: =IFERROR(C20/B20,0) | E20: =COUNTIFS(Features!B:B,"Team & Portfolio",Features!H:H,"v1.0") | F20: =COUNTIFS(Features!B:B,"Team & Portfolio",Features!H:H,"v1.5") | G20: =COUNTIFS(Features!B:B,"Team & Portfolio",Features!H:H,"v2.0") | H20: =COUNTIFS(Features!B:B,"Team & Portfolio",Features!H:H,"v2.5") | I20: =COUNTIFS(Features!B:B,"Team & Portfolio",Features!H:H,"v3.0+") | J20: =COUNTIFS(Features!B:B,"Team & Portfolio",Features!H:H,"Skip")
A21: Admin & Ops | B21: =COUNTIF(Features!B:B,"Admin & Ops") | C21: =COUNTIFS(Features!B:B,"Admin & Ops",Features!J:J,"Yes") | D21: =IFERROR(C21/B21,0) | E21: =COUNTIFS(Features!B:B,"Admin & Ops",Features!H:H,"v1.0") | F21: =COUNTIFS(Features!B:B,"Admin & Ops",Features!H:H,"v1.5") | G21: =COUNTIFS(Features!B:B,"Admin & Ops",Features!H:H,"v2.0") | H21: =COUNTIFS(Features!B:B,"Admin & Ops",Features!H:H,"v2.5") | I21: =COUNTIFS(Features!B:B,"Admin & Ops",Features!H:H,"v3.0+") | J21: =COUNTIFS(Features!B:B,"Admin & Ops",Features!H:H,"Skip")
A22: Infra | B22: =COUNTIF(Features!B:B,"Infra") | C22: =COUNTIFS(Features!B:B,"Infra",Features!J:J,"Yes") | D22: =IFERROR(C22/B22,0) | E22: =COUNTIFS(Features!B:B,"Infra",Features!H:H,"v1.0") | F22: =COUNTIFS(Features!B:B,"Infra",Features!H:H,"v1.5") | G22: =COUNTIFS(Features!B:B,"Infra",Features!H:H,"v2.0") | H22: =COUNTIFS(Features!B:B,"Infra",Features!H:H,"v2.5") | I22: =COUNTIFS(Features!B:B,"Infra",Features!H:H,"v3.0+") | J22: =COUNTIFS(Features!B:B,"Infra",Features!H:H,"Skip")
A23: TOTAL | B23: =SUM(B2:B22) | C23: =SUM(C2:C22) | D23: =IFERROR(C23/B23,0) | E23: =SUM(E2:E22) | F23: =SUM(F2:F22) | G23: =SUM(G2:G22) | H23: =SUM(H2:H22) | I23: =SUM(I2:I22) | J23: =SUM(J2:J22)

Sheet Release Plan
A1: Release | B1: Name | C1: Approx Effort | D1: What ships | E1: What CUSTOMER gets | F1: Critical to ship?
A2: v1.0 | B2: MVP | C2: ~6 weeks | D2: 5 custom objects (ForensicScan / ForensicFinding / AttributionTrace / RecoveryAction / CheckSuppression) • 5 highest-$ detectors (REN-001, REN-002, DSC-FOR-001, ORD-FOR-001, QL-FOR-001) • Class A + B attribution • Finding detail page • Stage → Approve → Mark Committed workflow • Commit verification • Score band header • Revenue Leakage card (basic) • Recovery queue • 1399 unit tests rewritten as Apex | E2: Click "Run Scan" inside Salesforce. See total leakage in $. Drill into top findings. Approve fixes. Apply them via in-org button (no Data Loader detour needed). Verify the fix landed. | F2: MUST SHIP
A3: v1.5 | B3: Coverage | C3: ~4 weeks | D3: Remaining 15 detectors • Class C, D, E tracers • Filter bar (search + effort + severity + hidden) • Hide / restore • Bulk select + bulk-stage + bulk-hide • Notes (DB + editor + indicator) • Issues bulk acknowledge/resolve • check_suppressions • Top Issues curated list • Effort badge per row • Card error UI | E3: Full detector coverage. Power-user workflow: search, filter, multi-select, bulk approve. Notes per finding for engagement context. Mark known false-positives so future scans skip them. | F3: STRONGLY RECOMMEND
A4: v2.0 | B4: Polish | C4: ~4 weeks | D4: $-Impact × Effort matrix card • Click-to-drill modal • 6-tab navigation • URL deep-links • Theme card grouping • Pricing Discipline + CPQ Complexity cards • Score Trend + Since Last Scan diff • Attribution Map page • Note popover (inline edit) • Scan history page • Plain-English label sweep • Typography hierarchy • Mobile responsive | E4: Sales-ready dashboard. "What to fix first" matrix becomes the pitch slide. Org history trend visible. Consultant can demo full audit-to-recovery on a screenshare. | F4: RECOMMENDED
A5: v2.5 | B5: Hard Stuff | C5: ~6 weeks | D5: AI explanations (batch via Apex callout to Gemini) • Executive PDF report (Visualforce) • Email notifications (Apex SingleEmail) • Scheduled scans (Scheduled Apex) • Onboarding wizard • Profile + revenue assumptions • Dark mode (SLDS) • AST-FOR-001 + Asset/Billing detector • Team activity audit trail | E5: Production-grade. AI explains what every finding means. Scans run on a schedule. PDF report for the client meeting. Customer onboarding becomes hands-off. | F5: NICE TO HAVE
A6: v3.0+ | B6: Future | C6: TBD | D6: Draggable tab reorder • Industry benchmarks (cross-org dataset) • Whatever doesn't fit above | E6: Polish + delight features. | F6: OPTIONAL
A7: Skip | B7: Won't Migrate | C7: N/A | D7: Multi-org portfolio dashboard • Compare-two-orgs view • Team invitations + workspaces • Admin dashboard • Public status page • Plan quotas (Free/Pro/Enterprise) • Trust scores + feedback digest • OAuth + Connected App • Vercel hosting • Supabase DB • Email/password auth • Header width tuning • Empty-error guards | E7: These are SaaS-only or cross-org features. The managed-package install model is single-org-per-install — these don't translate. | F7: DO NOT MIGRATE
A9: CUMULATIVE TIMELINE
A10: After v1.0 | B10: Week 6 | D10: AppExchange-listable MVP. Can demo end-to-end audit-to-recovery flow on a Salesforce-native dashboard. Top 5 detectors cover ~70% of $-impact in a typical org.
A11: After v1.5 | B11: Week 10 | D11: Full detector coverage. Consultants can run real audits and capture engagement notes. Bulk workflows make 50-finding reviews tractable.
A12: After v2.0 | B12: Week 14 | D12: Production-ready dashboard. Matrix + tabs + trend make this a real Hubbl competitor. Visual parity achieved.
A13: After v2.5 | B13: Week 20 | D13: AI + PDF + scheduled-scan parity with SaaS version. Last gap: multi-org portfolio (which is structurally incompatible with managed-package model).

Sheet Migration Reality Check
A1: Topic | B1: What it means for OrgPrism → Managed Package
A2: Current architecture | B2: Next.js 14 + Supabase Postgres + Vercel + jsforce + Gemini AI + Resend email + @react-pdf/renderer. ZERO Salesforce metadata exists today. The repo has no Apex classes, no LWC, no custom objects, no Flows.
A3: What "managed package" requires | B3: Apex code, Lightning Web Components, Custom Objects + Fields, Validation Rules, Flows, Permission Sets, Static Resources. All packaged into a 1GP or 2GP managed package, distributed via AppExchange.
A4: Honest effort estimate | B4: Full rewrite (v1.0 + v1.5 + v2.0): ~14 weeks for one Salesforce dev. Add v2.5 for ~20 weeks. The Release Plan tab breaks down what ships per release.
A5: What gets LOST in the migration | B5: (1) Multi-org portfolio dashboard — consultants lose their cross-org view. Each install only sees its own org. (2) AI explanations limited by Apex governor + callout limits. (3) Cross-engagement notes — each consultant must re-log notes per install. (4) PDF reports degraded (Visualforce is limited vs React-PDF). (5) Custom auth flow.
A6: What gets EASIER | B6: (1) Customer data never leaves their org — easier security review. (2) AppExchange = real discovery channel. (3) Salesforce admins prefer in-org tools. (4) Setup deep-links work natively. (5) Lightning datatable is excellent for selection + filtering. (6) No Data Loader detour — direct DML can apply fixes.
A7: Hubbl's actual architecture | B7: Hubbl is NOT a managed package. It is a SaaS web app at app.hubbl.com that reads metadata via OAuth. They distribute via AppExchange listing only. Same model as Salto, Provar, GearsetCM. Mention this so the founder calibrates expectations.
A8: Required for AppExchange listing | B8: Security Review (multi-week back-and-forth with Salesforce). Apex test coverage ≥75%. SOC2-equivalent documentation. Pen-test report. Costs ~$5-10K for partner setup + listing fees.
A9: The trap to avoid | B9: Don't conflate "we should be on AppExchange" with "we should be Apex-native." These are independent decisions. You can be on AppExchange WITHOUT being Apex-native (most SaaS vendors do this for years before going managed).
A10: Excel checkbox legend | B10: In the Features tab, "Deployed (Package)" column has a Yes/No/Partial dropdown. Mark Yes once a feature is re-implemented in the managed package. Conditional formatting turns the cell green on Yes, amber on Partial. The Summary tab shows progress per category. The Release Plan tab shows what should ship in which version.
A11: Apex Effort legend | B11: Easy = direct SOQL/data port. Medium = needs Custom Object + Apex glue. Hard = AI/PDF/cross-org dependency that fights Apex constraints. Skip = SaaS-only feature with no in-Salesforce equivalent (auth, hosting, multi-tenant DB, etc.). Skip rows total ~25 features that will NEVER migrate by design.
A12: Phase legend | B12: v1.0 = MVP (~6w), v1.5 = Coverage (~4w), v2.0 = Polish (~4w), v2.5 = Hard Stuff (~6w), v3.0+ = Future, Skip = Won't migrate. The Release Plan tab has full per-version detail.
